{
    "title_first" : "Remodelar é criar ",
    "title_second" : "o futuro a partir do passado",
    "content" : "Bastante solicitado pelos nossos clientes , pequenas remodelações que transformam espaços datados pelo tempo em espaços atuais e harmoniosos. A preservação da alma da casa e suas características únicas são uma prioridade para nós.",
    "img1": "url(https://storage.googleapis.com/eco-lar-bucket/Atlier/shutterstock_1854684700.jpg)",
    "img2": "url(https://storage.googleapis.com/eco-lar-bucket/montagens/IMG_138.jpg)",
    "img3":"url(https://storage.googleapis.com/eco-lar-bucket/Atlier/shutterstock_2234043077.jpg)",
    "proj": "Remodelações",
    "proj2": "concluídas"

}